dvs_printf/__Loading.py
dvs_printf/__init.py
dvs_printf/__init__.py
dvs_printf/__printf__.py
dvs_printf/other_styles.py
tests/.DS_Store
tests/__init__.py
tests/test_Competiblity/test_Numpy.py
tests/test_Competiblity/test_Pandas.py
tests/test_Competiblity/test_PyTorch.py
tests/test_Competiblity/test_Tensorflow.py
tests/test_Competiblity/test_listArray.py
tests/test__Functionlity/test_initionlizer.py
tests/test__Functionlity/test_list_of_str.py
tests/test__Functionlity/test_printf.py
tests/test__Functionlity/test_showLoading.py
tests/test__Functionlity/test_str_divide_line.py
dvs_printf-2.2.dist-info/LICENSE
dvs_printf-2.2.dist-info/METADATA
dvs_printf-2.2.dist-info/WHEEL
dvs_printf-2.2.dist-info/top_level.txt
dvs_printf-2.2.dist-info/RECORD
