Metadata-Version: 2.1
Name: dvs_printf
Version: 2.2
Summary: Animated Visual appearance for console-based applications, with different animation styles
Home-page: https://github.com/dhruvan-vyas/dvs_printf
Author: Dhruvan Vyas
Maintainer: dhruvan_vyas
License: MIT
Project-URL: Source, https://github.com/dhruvan-vyas/dvs_printf
Project-URL: Documentation, https://github.com/dhruvan-vyas/dvs_printf/blob/main/README.md
Project-URL: Tracker, https://github.com/dhruvan-vyas/dvs_printf/issues
Keywords: printf,animation,console,terminal
Classifier: Development Status :: 5 - Production/Stable
Classifier: Intended Audience :: Developers
Classifier: License :: OSI Approved :: MIT License
Classifier: Programming Language :: Python :: 3
Classifier: Programming Language :: Python :: 3.10
Classifier: Programming Language :: Python :: 3.11
Classifier: Programming Language :: Python :: 3.12
Classifier: Operating System :: OS Independent
Classifier: Topic :: Software Development :: Libraries :: Python Modules
Classifier: Topic :: Terminals
Classifier: Environment :: Console
Requires-Python: >=3.10
License-File: LICENSE
